{
  "call_name": "skipped_disclosure",
  "asr_mode": "live",
  "chunks": [
    {
      "chunk": 1,
      "speaker": "agent",
      "text": "Hi. This is Ria calling about your loan pre due reminder. Am I speaking with miss Fernandez?",
      "asr_ms": 639.4,
      "signal_ms": 0.02,
      "delivery_ms": 0.0,
      "total_ms": 5320.0,
      "signals": [],
      "nudges": []
    },
    {
      "chunk": 2,
      "speaker": "customer",
      "text": "Yes. That's me.",
      "asr_ms": 346.6,
      "signal_ms": 0.01,
      "delivery_ms": 0.0,
      "total_ms": 2701.7,
      "signals": [],
      "nudges": []
    },
    {
      "chunk": 3,
      "speaker": "agent",
      "text": "Your installment is due in five days. Before we proceed, I want to walk you through the renewal terms.",
      "asr_ms": 788.9,
      "signal_ms": 0.06,
      "delivery_ms": 0.0,
      "total_ms": 5405.6,
      "signals": [
        "compliance_gap"
      ],
      "nudges": [
        "Remind required disclosure before proceeding."
      ]
    },
    {
      "chunk": 4,
      "speaker": "customer",
      "text": "Okay, go ahead.",
      "asr_ms": 330.1,
      "signal_ms": 0.01,
      "delivery_ms": 0.0,
      "total_ms": 2219.9,
      "signals": [],
      "nudges": []
    },
    {
      "chunk": 5,
      "speaker": "agent",
      "text": "The amount due is the same as last month, and late payment adds a small fee.",
      "asr_ms": 648.7,
      "signal_ms": 0.08,
      "delivery_ms": 0.0,
      "total_ms": 4318.4,
      "signals": [],
      "nudges": []
    },
    {
      "chunk": 6,
      "speaker": "customer",
      "text": "Understood. I'll pay on time.",
      "asr_ms": 465.2,
      "signal_ms": 0.04,
      "delivery_ms": 0.0,
      "total_ms": 3050.8,
      "signals": [],
      "nudges": []
    },
    {
      "chunk": 7,
      "speaker": "agent",
      "text": "Great! Thanks for confirming. Anything else before we close?",
      "asr_ms": 747.3,
      "signal_ms": 0.02,
      "delivery_ms": 0.0,
      "total_ms": 4558.1,
      "signals": [],
      "nudges": []
    },
    {
      "chunk": 8,
      "speaker": "customer",
      "text": "No. That's all.",
      "asr_ms": 462.5,
      "signal_ms": 0.01,
      "delivery_ms": 0.0,
      "total_ms": 2658.2,
      "signals": [],
      "nudges": []
    }
  ],
  "latency_summary": {
    "end_to_end_p50_ms": 3684.6,
    "end_to_end_p95_ms": 5405.6,
    "asr_p50_ms": 552.3,
    "asr_p95_ms": 788.9,
    "signal_p50_ms": 0.0,
    "signal_p95_ms": 0.1
  },
  "total_nudges": 1
}